MANIFEST.in
README.rst
setup.py
dpostools/__init__.py
dpostools/api.py
dpostools/constants.py
dpostools/dbtools.py
dpostools/exceptions.py
dpostools/legacy.py
dpostools/legacy_constants.py
dpostools/misc.py
dpostools/schemes.py
dpostools/utils.py
dpostools.egg-info/PKG-INFO
dpostools.egg-info/SOURCES.txt
dpostools.egg-info/dependency_links.txt
dpostools.egg-info/requires.txt
dpostools.egg-info/top_level.txt
dpostools/tests/__init__.py
dpostools/tests/legacy_tests.py
dpostools/tests/test_api.py
dpostools/tests/test_ark_node.py
dpostools/tests/test_blockchain.py
dpostools/tests/test_oxy_node.py
dpostools/yamls/arkdbschema.yaml
dpostools/yamls/basedbschema.yaml
dpostools/yamls/kapudbschema.yaml
dpostools/yamls/oxycoindbschema.yaml
park/__init__.py
park/park.py
park/api/__init__.py
park/api/account.py
park/api/api.py
park/api/block.py
park/api/delegate.py
park/api/loader.py
park/api/multisignature.py
park/api/peer.py
park/api/signature.py
park/api/transaction.py
park/api/transport.py
park/api/vote.py
park/builder/__init__.py
park/builder/builder.py
park/builder/delegate.py
park/builder/multisignature.py
park/builder/signature.py
park/builder/transaction.py
park/builder/vote.py