Metadata-Version: 1.0
Name: dpostools
Version: 0.1.0
Summary: generic toolkit for interacting with DPOS chains
Home-page: https://github.com/BlockHub/blockhubdpostools.git
Author: Charles
Author-email: karel@blockhub.nl
License: MIT
Platform: UNKNOWN
